tacrpy/__init__.py
tacrpy/data_operations.py
tacrpy/analytics/__init__.py
tacrpy/data_fetcher/__init__.py
tacrpy/data_fetcher/googlesheets.py
tacrpy/data_fetcher/isvavai.py
tacrpy/data_fetcher/ssot.py
tacrpy/datahub/__init__.py
tacrpy/datahub/data_lineage.py
tacrpy/datahub/datasets.py
tacrpy/datahub/glossary.py
tacrpy/datahub/import_checks.py
tacrpy/datahub/openapi.py
tacrpy/nlp/__init__.py
tacrpy/nlp/fulltext.py
tacrpy/nlp/preprocessing.py
tacrpy/nlp/semantic.py
tacrpy-2.4.17.dist-info/METADATA
tacrpy-2.4.17.dist-info/WHEEL
tacrpy-2.4.17.dist-info/top_level.txt
tacrpy-2.4.17.dist-info/RECORD
