Metadata-Version: 2.1
Name: tacrpy
Version: 2.4.17
Summary: Analytická knihovna pro potřeby TA ČR
Home-page: UNKNOWN
Author: david.sulc
Author-email: sulda.str@gmail.com
License: UNKNOWN
Project-URL: Documentation, https://data.tacr.cz/tacrpy/docs/index.html
Platform: UNKNOWN
Requires-Dist: pandas
Requires-Dist: gspread
Requires-Dist: numpy
Requires-Dist: sentence-transformers
Requires-Dist: nltk
Requires-Dist: requests
Requires-Dist: corpy
Requires-Dist: unidecode
